{
  "last_updated": "2026-01-15T23:15:10.657947",
  "available_dates": [
    "2026-01-16",
    "2026-01-15",
    "2026-01-14",
    "2026-01-13",
    "2026-01-12",
    "2026-01-11",
    "2026-01-10",
    "2026-01-09",
    "2026-01-08",
    "2026-01-07",
    "2026-01-06",
    "2026-01-05",
    "2026-01-04",
    "2026-01-03",
    "2026-01-02",
    "2026-01-01",
    "2025-12-31",
    "2025-12-30",
    "2025-12-29",
    "2025-12-28",
    "2025-12-27",
    "2025-12-26",
    "2025-12-25",
    "2025-12-24",
    "2025-12-23",
    "2025-12-22",
    "2025-12-21",
    "2025-12-20",
    "2025-12-19",
    "2025-12-18",
    "2025-12-17"
  ],
  "dates_detail": {
    "2026-01-16": [
      {
        "period": "morning",
        "file": "2026-01-16-morning.json",
        "period_label": "오전"
      }
    ],
    "2026-01-15": [
      {
        "period": "morning",
        "file": "2026-01-15-morning.json",
        "period_label": "오전"
      },
      {
        "period": "afternoon",
        "file": "2026-01-15-afternoon.json",
        "period_label": "오후"
      }
    ],
    "2026-01-14": [
      {
        "period": "morning",
        "file": "2026-01-14-morning.json",
        "period_label": "오전"
      },
      {
        "period": "afternoon",
        "file": "2026-01-14-afternoon.json",
        "period_label": "오후"
      }
    ],
    "2026-01-13": [
      {
        "period": "morning",
        "file": "2026-01-13-morning.json",
        "period_label": "오전"
      },
      {
        "period": "afternoon",
        "file": "2026-01-13-afternoon.json",
        "period_label": "오후"
      }
    ],
    "2026-01-12": [
      {
        "period": "morning",
        "file": "2026-01-12-morning.json",
        "period_label": "오전"
      },
      {
        "period": "afternoon",
        "file": "2026-01-12-afternoon.json",
        "period_label": "오후"
      }
    ],
    "2026-01-11": [
      {
        "period": "morning",
        "file": "2026-01-11-morning.json",
        "period_label": "오전"
      },
      {
        "period": "afternoon",
        "file": "2026-01-11-afternoon.json",
        "period_label": "오후"
      }
    ],
    "2026-01-10": [
      {
        "period": "morning",
        "file": "2026-01-10-morning.json",
        "period_label": "오전"
      },
      {
        "period": "afternoon",
        "file": "2026-01-10-afternoon.json",
        "period_label": "오후"
      }
    ],
    "2026-01-09": [
      {
        "period": "morning",
        "file": "2026-01-09-morning.json",
        "period_label": "오전"
      },
      {
        "period": "afternoon",
        "file": "2026-01-09-afternoon.json",
        "period_label": "오후"
      }
    ],
    "2026-01-08": [
      {
        "period": "morning",
        "file": "2026-01-08-morning.json",
        "period_label": "오전"
      },
      {
        "period": "afternoon",
        "file": "2026-01-08-afternoon.json",
        "period_label": "오후"
      }
    ],
    "2026-01-07": [
      {
        "period": "morning",
        "file": "2026-01-07-morning.json",
        "period_label": "오전"
      },
      {
        "period": "afternoon",
        "file": "2026-01-07-afternoon.json",
        "period_label": "오후"
      }
    ],
    "2026-01-06": [
      {
        "period": "morning",
        "file": "2026-01-06-morning.json",
        "period_label": "오전"
      },
      {
        "period": "afternoon",
        "file": "2026-01-06-afternoon.json",
        "period_label": "오후"
      }
    ],
    "2026-01-05": [
      {
        "period": "morning",
        "file": "2026-01-05-morning.json",
        "period_label": "오전"
      },
      {
        "period": "afternoon",
        "file": "2026-01-05-afternoon.json",
        "period_label": "오후"
      }
    ],
    "2026-01-04": [
      {
        "period": "morning",
        "file": "2026-01-04-morning.json",
        "period_label": "오전"
      },
      {
        "period": "afternoon",
        "file": "2026-01-04-afternoon.json",
        "period_label": "오후"
      }
    ],
    "2026-01-03": [
      {
        "period": "morning",
        "file": "2026-01-03-morning.json",
        "period_label": "오전"
      },
      {
        "period": "afternoon",
        "file": "2026-01-03-afternoon.json",
        "period_label": "오후"
      }
    ],
    "2026-01-02": [
      {
        "period": "morning",
        "file": "2026-01-02-morning.json",
        "period_label": "오전"
      },
      {
        "period": "afternoon",
        "file": "2026-01-02-afternoon.json",
        "period_label": "오후"
      }
    ],
    "2026-01-01": [
      {
        "period": "morning",
        "file": "2026-01-01-morning.json",
        "period_label": "오전"
      },
      {
        "period": "afternoon",
        "file": "2026-01-01-afternoon.json",
        "period_label": "오후"
      }
    ],
    "2025-12-31": [
      {
        "period": "morning",
        "file": "2025-12-31-morning.json",
        "period_label": "오전"
      },
      {
        "period": "afternoon",
        "file": "2025-12-31-afternoon.json",
        "period_label": "오후"
      }
    ],
    "2025-12-30": [
      {
        "period": "morning",
        "file": "2025-12-30-morning.json",
        "period_label": "오전"
      },
      {
        "period": "afternoon",
        "file": "2025-12-30-afternoon.json",
        "period_label": "오후"
      }
    ],
    "2025-12-29": [
      {
        "period": "morning",
        "file": "2025-12-29-morning.json",
        "period_label": "오전"
      },
      {
        "period": "afternoon",
        "file": "2025-12-29-afternoon.json",
        "period_label": "오후"
      }
    ],
    "2025-12-28": [
      {
        "period": "morning",
        "file": "2025-12-28-morning.json",
        "period_label": "오전"
      },
      {
        "period": "afternoon",
        "file": "2025-12-28-afternoon.json",
        "period_label": "오후"
      }
    ],
    "2025-12-27": [
      {
        "period": "morning",
        "file": "2025-12-27-morning.json",
        "period_label": "오전"
      },
      {
        "period": "afternoon",
        "file": "2025-12-27-afternoon.json",
        "period_label": "오후"
      }
    ],
    "2025-12-26": [
      {
        "period": "morning",
        "file": "2025-12-26-morning.json",
        "period_label": "오전"
      },
      {
        "period": "afternoon",
        "file": "2025-12-26-afternoon.json",
        "period_label": "오후"
      }
    ],
    "2025-12-25": [
      {
        "period": "morning",
        "file": "2025-12-25-morning.json",
        "period_label": "오전"
      },
      {
        "period": "afternoon",
        "file": "2025-12-25-afternoon.json",
        "period_label": "오후"
      }
    ],
    "2025-12-24": [
      {
        "period": "morning",
        "file": "2025-12-24-morning.json",
        "period_label": "오전"
      },
      {
        "period": "afternoon",
        "file": "2025-12-24-afternoon.json",
        "period_label": "오후"
      }
    ],
    "2025-12-23": [
      {
        "period": "morning",
        "file": "2025-12-23-morning.json",
        "period_label": "오전"
      },
      {
        "period": "afternoon",
        "file": "2025-12-23-afternoon.json",
        "period_label": "오후"
      }
    ],
    "2025-12-22": [
      {
        "period": "morning",
        "file": "2025-12-22-morning.json",
        "period_label": "오전"
      },
      {
        "period": "afternoon",
        "file": "2025-12-22-afternoon.json",
        "period_label": "오후"
      }
    ],
    "2025-12-21": [
      {
        "period": "morning",
        "file": "2025-12-21-morning.json",
        "period_label": "오전"
      },
      {
        "period": "afternoon",
        "file": "2025-12-21-afternoon.json",
        "period_label": "오후"
      }
    ],
    "2025-12-20": [
      {
        "period": "morning",
        "file": "2025-12-20-morning.json",
        "period_label": "오전"
      },
      {
        "period": "afternoon",
        "file": "2025-12-20-afternoon.json",
        "period_label": "오후"
      }
    ],
    "2025-12-19": [
      {
        "period": "morning",
        "file": "2025-12-19-morning.json",
        "period_label": "오전"
      },
      {
        "period": "afternoon",
        "file": "2025-12-19-afternoon.json",
        "period_label": "오후"
      }
    ],
    "2025-12-18": [
      {
        "period": "afternoon",
        "file": "2025-12-18-afternoon.json",
        "period_label": "오후"
      }
    ],
    "2025-12-17": [
      {
        "period": "full",
        "file": "2025-12-17.json",
        "period_label": "전체"
      }
    ]
  },
  "latest": "2026-01-16-morning",
  "total_briefings": 59
}